{
  "id": "unknown-exam-6e4c6833ee0e33f71e8c998ea9f39344",
  "year": null,
  "type": "exam",
  "source": {
    "fileName": "111 - 104. Knee Arthritis.pdf",
    "filePath": "/Users/camilosar/Documents/Antigravity/fearless-davinci/docs/guidelines/DeLee, Drez, & Miller's Orthopaedic Sports Medicine, Fifth Edition/111 - 104. Knee Arthritis.pdf"
  },
  "pageCount": 21,
  "pages": [
    {
      "pageNumber": 1,
      "text": "1277\nKnee Arthritis\nCatherine Hui, Stephen R. Thompson, J. Robert Giffin\n104 \nKnee osteoarthritis (OA) is an extremely common cause of dis-\nability. The etiology is multifactorial, but joint injury is a prevalent \ncause of OA in the knee. 1,2 Studies have shown that meniscal \ninjury requiring a meniscectomy alters knee biomechanics and \nleads to gonarthrosis.\n3 Anterior cruciate ligament (ACL) rupture, \na frequently seen and often devastating injury, is characteristi -\ncally associated with meniscal and chondral injuries. 4 Further \ndeterioration of the joint related to multiple subluxation episodes \nover time leads to gonarthrosis, which typically affects the medial \ncompartment and results in varus deformity.\n5–9\nHISTORY\nA thorough history will rule out systemic causes of pain, such \nas rheumatoid or other inflammatory arthritides, as well as \nreferred hip pain or radiating pain resulting from degenerative \ndisk disease. Patients with knee OA usually present with pain. \nOther symptoms include catching, locking, swelling, and decreased \nmotion.\n1,10,11 Instability is a frequent complaint, but in general \nit represents quadriceps weakness rather than true ligamentous \ninstability.\n12 Patients with chronic ACL deficiency in whom medial \ncompartment gonarthrosis with subsequent varus deformity has \ndeveloped may experience pain and/or instability. However, in \nthese patients pain is the most common presenting symptom, \nand instability may not be present as a result of the constraint \nacquired through the degenerative process and the development \nof a “cupula” from posteromedial tibial wear.\n8 Table 104.1 outlines \nkey questions for patients presenting with knee OA.\nPHYSICAL EXAMINATION\nA systematic approach to the physical examination of the knee \nincludes inspection, palpation, range of motion (ROM), and \nspecial tests when appropriate. A comparison of the affected \nand nonaffected limbs, an examination of the joints above and \nbelow the affected knee, and an assessment of the patient’s distal \nneurovascular status are routine components of the physical \nexamination.\n13,14\nThe inspection begins with an evaluation of limb alignment \nboth while the patient is standing and walking. Varus, valgus, \nor neutral alignment is noted, as well as an antalgic or Tren -\ndelenburg gait or a thrust (i.e., a dynamic change in the deformity \nwith weight bearing).\n13,15 If possible, the patient should perform \na full squat and the duck walk (Childress sign). Pain with either \nor both of these activities suggests a meniscal tear. 16 Any previ-\nous incisions should be noted.\nWith the patient seated and his or her knees flexed over the \nedge of the table, patellar position and quadriceps asymmetry, \nif present, are determined. Quadriceps reflex inhibition due to \nknee injury and effusion frequently leads to quadriceps atrophy.\n17,18\nAn effusion, which is characterized by asymmetry in the peri-\npatellar groove on either side of the patella, is confirmed with \nthe swipe test. This test is performed with the patient in the \nsupine position with his or her legs extended and relaxed. The \nexaminer strokes the medial side starting just below the joint line \nand moves toward the suprapatellar pouch and then does the \nsame on the lateral side while observing for a fluid-wave bulge \nmedially. The presence of a fluid wave indicates a positive swipe \ntest and confirms a small to medium intracapsular effusion.\n14\nThe patellar ballottement test identifies a moderate to severe \neffusion. With the knee in full extension, the examiner compresses \nthe patella toward the trochlea and then releases it. If fluid is \npresent, the patella will feel as if it were floating.\n14\nPalpation of the knee structures is performed in a methodical \nfashion and guided by the suspected diagnosis. The temperature \nof the knee to touch is compared with that of the opposite knee. \nIncreased warmth suggests the presence of inflammation. It is \nimportant to determine the point of maximal tenderness. Gener-\nally the area anticipated to be most tender is palpated last, so \nthat the patient will not be guarding during the remainder of \nthe examination.\n14\nROM compared with the contralateral knee is measured. \nPatellar tracking during ROM is palpated, as well as crepitus (a \npalpable grating sensation) during flexion and extension, with \nparticular attention to its specific location.\n14 Finally, the patient \nis asked to perform a straight leg raise to assess quadriceps strength \nand extensor mechanism function.\n14\nSpecial tests are then performed, including an assessment of \ncruciate and collateral stability (see Chapter 90). These tests are \nparticularly important to detect the presence of a chronically \ndeficient ACL.\nIMAGING\nRadiographs taken during weight bearing are the gold standard for \nimaging any knee condition, especially OA. The standard radio-\ngraphic knee series includes the following views: bilateral standing \nanteroposterior (AP), bilateral standing 45-degree posteroanterior \nDescargado para juan camilo sarmiento (z0500754a@saludcastillayleon.es) en Government of Castile and Leon Ministry of Health de ClinicalKey.es por Elsevier en \njunio 02, 2026. Para uso personal exclusivamente. No se permiten otros usos sin autorización. Copyright ©2026. Elsevier Inc. Todos los derechos reservados."
    },
    {
      "pageNumber": 2,
      "text": "1277.e1CHAPTER 104 Knee Arthritis\nKeywords\nathlete\ninjection\nknee\nosteoarthritis\ntibial osteotomy\nyoung adult\nAbstract\nKnee arthritis is a common condition in the athlete. In this \nchapter, we discuss our approach to the athlete with knee arthritis, \nincluding a discussion of the various injection modalities and \nsurgical options. Our preferred method of treatment is a medial \nopening wedge high tibial osteotomy. Risks and complications \nare also discussed.\nDescargado para juan camilo sarmiento (z0500754a@saludcastillayleon.es) en Government of Castile and Leon Ministry of Health de ClinicalKey.es por Elsevier en \njunio 02, 2026. Para uso personal exclusivamente. No se permiten otros usos sin autorización. Copyright ©2026. Elsevier Inc. Todos los derechos reservados."
    },
    {
      "pageNumber": 3,
      "text": "1278 SECTION 7 Knee\ncenter of the knee in a neutrally aligned limb. Any deviation \nfrom this point is considered malalignment. If the line falls toward \nthe medial side of the knee, the limb is in varus alignment; if \nthe line falls toward the lateral side of the knee, the limb is in \nvalgus alignment.\n26\nSagittal plane alignment is determined by measuring the \nposterior tibial slope. This angle is defined by a line perpendicular \nto the mid-diaphysis of the tibia and the posterior inclination \nof the tibial plateau on a lateral radiograph.\n27\nRadiographs also identify signs of OA and its severity (e.g., \nosteophytes, joint space narrowing, subchondral sclerosis, and \nsubchondral cysts), which areas of the knee are affected, limb \nalignment, posterior tibial slope, patellar height, previous fracture, \ndeformity, and previous surgery as well as previous implants \nused and the location of the implants.\nMagnetic resonance imaging (MRI) is a commonly ordered \ninvestigation in patients who present with knee conditions. \nHowever, most of the information required for decision-making \nin patients with knee OA can be gathered from a proper history, \nphysical examination, and the aforementioned radiographs.\n19 \nBhattacharyya et al.28 reviewed radiographs and MRI images in \n154 patients (men ≥45 years; women ≥50 years) with symptomatic \nand asymptomatic knee OA. The groups were similar in age. \nHowever, patients in the symptomatic OA group had significantly \nhigher body mass index (BMI) scores. The authors found that \nmeniscal tears were highly prevalent in both asymptomatic (76%) \nand symptomatic (91%) cases of knee OA. Increased radiographic \nevidence of OA was associated with an increased rate of meniscal \ntears. No significant difference in pain and function was found \non a visual analog scale or the Western Ontario and McMaster \nUniversities Osteoarthritis Index (WOMAC) scores between \npatients with and without a medial or lateral meniscal tear in \nthe osteoarthritic group. Ultimately the etiology of pain in patients \nwith knee OA is multifactorial and can include cartilage lesions, \nsynovial inflammation, and periarticular muscle strains. The \nQuestion Patient Response\nIdentification Age, occupation\nChief complaint Pain/clicking/locking/swelling/decreased \nmotion/instability\nHistory of presenting \nillness\nPain history\nW: Where is most of the pain located? \n(point with finger)\nW: When did it start?\nQ: Quality of the pain; does it radiate?\nQ: Quantity of pain\nA: Aggravating factors\nA: Alleviating factors\nA: Associated symptoms\nAssociated trauma or injury\nMechanism of injury\nDate\nTreatment\nTreatments to date Analgesics, NSAIDs, bracing, physiotherapy, \ninjections, surgery\nFunctional status Walking tolerance (no. of blocks) as limited \nby knee symptoms\nSleep disturbance\nPain at rest\nADLs\nSports\nExpectations Return to physical work\nReturn to sports and activities\nLevel of competition\nHigh-impact versus low-impact activities\nTABLE 104.1 Key Questions for Patients \nPresenting With Knee Osteoarthritis\nADLs, Activities of daily living; NSAIDs, nonsteroidal antiinflammatory \ndrugs.\nAB\nFig. 104.1  (A) A conventional standing anteroposterior radiograph of \nthe right knee with no visible joint space narrowing. (B) A “Rosenberg \nview” of the same knee shows evidence of joint space narrowing and \nosteoarthritis. \n(PA) flexion, and lateral and skyline of the affected knee. The \nspecific purpose of the two standing films is to identify joint \nspace narrowing compared with the nonaffected knee.\n19–21\nThe weight-bearing 45-degree PA flexion radiograph was first \ndescribed by Rosenberg et  al.21 in 1988 and is often referred to \nas the Rosenberg view (Fig. 104.1). The authors noted that some \npatients for whom no joint space narrowing was visible on stand-\ning full-extension AP views often were found to have areas of \nsignificant cartilage wear at the time of arthroscopy. As the knee \nis flexed during the stance phase of gait, the femorotibial contact \narea moves posteriorly and decreases in size, so that force per \nunit area loading of the knee is increased. Therefore the flexed \nknee is much more susceptible to chondral damage and subse -\nquent OA. Furthermore, in patients with ACL deficiency, the \naltered knee biomechanics lead to increased posteromedial wear, \nparticularly on the tibia. For these reasons, the Rosenberg view \nhas better sensitivity and specificity than the conventional stand-\ning AP radiograph in detecting joint space narrowing and OA.\n20,21\nIf joint space narrowing is observed on the standard knee \nseries, a standing hip to ankle radiograph should be obtained \nto assess limb alignment (Fig. 104.2). This view is critical for \ndecision-making and surgical planning.\n22–24 A line from the center \nof the hip to the center of the ankle defines the mechanical axis \nin the coronal plane.\n25 This line generally passes through the \nDescargado para juan camilo sarmiento (z0500754a@saludcastillayleon.es) en Government of Castile and Leon Ministry of Health de ClinicalKey.es por Elsevier en \njunio 02, 2026. Para uso personal exclusivamente. No se permiten otros usos sin autorización. Copyright ©2026. Elsevier Inc. Todos los derechos reservados."
    },
    {
      "pageNumber": 4,
      "text": "1279CHAPTER 104 Knee Arthritis\nNonoperative Treatment Options\nEducation and Activity Modification\nThe natural history of OA is a waxing and waning course, with days \nwhen symptoms are manageable and days when symptoms seem \nto worsen. Patients should be educated about self-management \ntechniques, including lifestyle and activity modification. Encour-\naging patients to take responsibility for their condition allows \nthem to actively participate in their care and has been shown \nto improve symptoms.\n29,30\nWeight Loss\nPatients with symptomatic knee OA who have a BMI score of \nmore than 25 k g/m2 should be encouraged to lose weight through \ndiet and exercise. Studies have shown an improvement in overall \nclinical function in the WOMAC function subscale with weight \nloss.\n29,30 Other studies have shown that weight reduction decreases \nthe knee joint load per step at a ratio of 1 l b lost to a 4-lb reduc-\ntion in knee-joint load per step. 31,32 Weight loss not only has a \nbeneficial effect on the symptoms of knee OA but also provides \nwhole-body health benefits that cannot be overlooked.\nLow-Impact Exercise\nMultiple studies have shown that low-impact exercise—such as \nwalking, biking, and using an elliptical trainer—has the beneficial \neffects of decreasing pain and disability in patients with knee \nOA.\n29,30 The American Geriatrics Society recommends a minimum \nof 20 to 30 minutes of physical activity per day two to five times \nper week for persons with OA.\n33\nAnalgesic Medications\nPatients who have a symptomatic osteoarthritic knee should be \nencouraged to use acetaminophen for pain relief. Studies com -\nparing the use of acetaminophen (≤\n4 g/d) w ith a placebo have \nshown significant benefit in pain relief without any significant \nadverse effects.\n29,30 In 2011, the US Food and Drug Administra-\ntion (FDA) recommended that the dose of acetaminophen be \nchanged to 3 g/day due to the risk of severe liver injury. 34\nAdditionally, ketorolac (Tramadol) has been shown to have \nsome benefit in the relief of pain and stiffness and improvement \nin function in patients with knee OA and may be considered.\n35\nNonsteroidal Antiinflammatory Drugs\nIn patients who have no risk factors for gastrointestinal disease, \nnonsteroidal antiinflammatory drugs (NSAIDs) may be prescribed \nfor pain relief. Studies have shown a statistically significant favor-\nable clinical response with the use of NSAIDs versus acetamino-\nphen. Consideration for additional gastroprotective medication \nalong with nonselective NSAID medication or cyclooxygenase-2 \ninhibitors is recommended. T opical NSAID medication has been \nshown to improve pain, stiffness, and function and should also \nbe considered.\n29,30\nBraces\nThe use of an unloader knee brace may be a cost-effective adjunct \nto treatment and a reasonable option to help decrease symptoms \nand increase function in patients with knee OA.\n36,37 This type \ninvestigators concluded that there is no indication for the routine \nuse of MRI in the evaluation and management of patients with \nOA of the knee.\n28\nTREATMENT OPTIONS\nFig. 104.3 shows possible treatment options, from least to most \ninvasive.\nFig. 104.2  This standing hip-to-ankle radiographic view is critical in \ndecision-making and surgical planning. A line from the center of the hip \nto the center of the ankle defines the mechanical axis in the coronal \nplane. In a neutrally aligned limb, this line passes through the center of \nthe knee. Any deviation from this point is considered malalignment. \nHere the line falls toward the medial side of the knee, indicating varus \nalignment of the limb. \nDescargado para juan camilo sarmiento (z0500754a@saludcastillayleon.es) en Government of Castile and Leon Ministry of Health de ClinicalKey.es por Elsevier en \njunio 02, 2026. Para uso personal exclusivamente. No se permiten otros usos sin autorización. Copyright ©2026. Elsevier Inc. Todos los derechos reservados."
    },
    {
      "pageNumber": 5,
      "text": "1280 SECTION 7 Knee\nPlatelet-rich plasma. Platelet-rich plasma (PRP) is derived \nfrom a patient’s own blood. Therapeutic injections of PRP involve \nconcentrating the levels of platelets in the plasma through ultra-\nhigh-speed centrifugation. Platelets secrete growth factors and \nproteins that stimulate tissue healing, and it is believed that this \ncan help to alleviate the symptoms of knee arthritis. At present \nthere is a paucity of evidence supporting the use of PRP in knee \narthritis and it should be used with caution.\n44\nStem cells. Mesenchymal stem cells from bone marrow are \nthe most common cells used in stem cell injections for OA. It \nis believed that these cells have the best potential for developing \ninto cartilage cells that can repair damaged cartilage, decrease \nthe rate of cartilage degeneration, suppress inflammation, and \ntherefore decrease pain. Similar to PRP injections in knee OA, \nthere is little evidence supporting the use of stem cell injections \nat present and they should be used with caution.\n45\nTreatment Not Recommended\nSeveral treatment options such as glucosamine and/or chon -\ndroitin, lateral heel wedges, and needle lavage have historically \nbeen prescribed as nonoperative treatment options for patients \nwith symptomatic OA of the knee. However, a sufficient number \nof high-quality studies have shown that glucosamine hydrochlo-\nride and/or chondroitin sulfate have no clinical benefit compared \nwith placebo.\n35,46 Likewise, no good evidence exists to support \nthe prescription of lateral heel wedges for MCOA of the knee.47 \nLast, studies recommending needle lavage have been of poor \nquality, and the procedure has not been shown to have any lasting \nbenefit.\n48,49\nOperative Options\nArthroscopy\nArthroscopic lavage, débridement, and/or meniscectomy are not \nrecommended in patients whose primary symptom is pain. In \n2002 Moseley et  al.50 conducted the first of two randomized \ncontrolled studies of the effect of arthroscopic surgery in patients \nwith OA of the knee who presented with knee pain. They com -\npared arthroscopic surgery with arthroscopic lavage and “sham” \nsurgery in 180 patients and found that results of arthroscopic \nsurgery were no better than those of sham surgery at a follow-up \nof 2 years.\n50 In 2008 Kirkley et al.1 conducted another random-\nized controlled trial with 188 patients in which arthroscopic \nof brace functions by helping to transfer the weight-bearing \nforces from the worn to the unworn part of the knee. Although \nit can be used for either varus or valgus deformities, it has been \nprimarily studied in patients with medial compartment OA \n(MCOA). In a study by Kirkley et  al.,37 a varus unloader brace \nwas shown to have significant benefit compared with a neoprene \nsleeve or medical management alone in decreasing pain and \nimproving function. The authors recommended its use in patients \nwith symptomatic unicompartmental OA who have a correctable \ndeformity and an average-sized leg.\n37 Also, the use of an unloader \nbrace may help to determine whether the patient will have any \nbenefit from a limb realignment procedure. A further advantage \nof bracing relates to proprioception. Studies have shown that \npatients with knee OA have decreased proprioception. Kirkley \net al.37 report that knee braces offer a proprioceptive benefit. \nThe disadvantages to bracing are compliance, difficulty in obtain-\ning a proper fit, and cost.\nPhysical Therapy\nQuadriceps-strengthening exercises have been shown to provide \na significant benefit for symptomatic pain relief. The use of ROM \nand stretching exercises has not been studied extensively and \ntheir clinical effect is unknown. However, flexibility and motion \nexercises appear to have no adverse effects and offer many health \nbenefits.\n38–40\nInjections\nCorticosteroid. Intra-articular corticosteroid injections may \nbe prescribed for the short-term relief of acute pain due to an \narthritic “flareup. ” Studies have shown that the mean duration \nof the effect of a corticosteroid injection is 1 week.\n41–43\nViscosupplementation. Recent studies suggest that there is \nno benefit to viscosupplementation injections with hyaluronic \nacid in patients with symptomatic knee OA. A meta-analysis did \ndemonstrate a statistically significant benefit of hyaluronic acid \ninjections with regard to WOMAC pain, stiffness, and function, \nbut these outcomes did not meet the clinically important improve-\nment thresholds. In addition, meta-analysis in meaningfully \nimportant difference (MID) units demonstrated a low likelihood \nof patients achieving clinically important benefits from these \ninjections. Based on these findings, we recommend against the \nuse of hyaluronic acid injections in symptomatic knee OA.\n35\nLess\ninvasive\nMore\ninvasive\nWeight\nloss\nPhysical\ntherapy Analgesics InjectionsO steotomy\nTotal knee\narthroplasty\nRest and activity\nmodification\nLow-impact\naerobic\nexercise\nBracing NSAIDs Arthroscopy Unicompartmental\nknee arthroplasty\nFig. 104.3 Treatment options from least to most invasive for patients with symptomatic osteoarthritis of \nthe knee. NSAIDs, Nonsteroidal antiinflammatory drugs. \nDescargado para juan camilo sarmiento (z0500754a@saludcastillayleon.es) en Government of Castile and Leon Ministry of Health de ClinicalKey.es por Elsevier en \njunio 02, 2026. Para uso personal exclusivamente. No se permiten otros usos sin autorización. Copyright ©2026. Elsevier Inc. Todos los derechos reservados."
    },
    {
      "pageNumber": 6,
      "text": "1281CHAPTER 104 Knee Arthritis\nThe advantages and disadvantages of each technique are outlined \nin Table 104.2.\nMedial opening wedge high tibial osteotomy.  Historically, \nalong with the points shown in Table 104.2, the concerns with \nmedial opening wedge HTO have been prolonged immobiliza-\ntion and restricted weight bearing, both of which have a significant \nimpact on the patient’s quality of life. Recent improvements in \nimplant technology have led to the development of locking plates \nfor HTO. These devices are much stronger than previous non -\nlocking implants and allow weight bearing as early as 2 weeks \nafter surgery with no loss of correction of the osteotomy and \nno delayed union or nonunion.\n63,64 Another concern with medial \nopening wedge HTO is the morbidity associated with the har -\nvesting of iliac crest bone graft required to fill the osteotomy. \nHowever, several recent studies have reported that an autograft, \nan allograft, and even no graft for corrections of 8  mm o r less \nhave produced good results, with union occurring by 12 weeks \nafter surgery.\n65,66\nLateral closing wedge high tibial osteotomy. Coventry67 first \ndescribed the technique of lateral closing wedge HTO in 1965. \nAdvantages and disadvantages are described in Table 104.2. Cur-\nrently our only indication for this procedure is a previous suc-\ncessful lateral closing wedge HTO in the contralateral limb.\nOther techniques.  Less commonly used tibial osteotomy \ntechniques include the dome osteotomy and external fixation. \nThese techniques are recommended for deformities greater than \n25 degrees as well for those that require gradual rather than \nacute correction, as in skeletally mature patients with Blount \ndisease or in younger patients with idiopathic genu varum.\n68–71\nsurgery was compared with optimized physiotherapy and medical \nmanagement. These investigators specifically addressed several \nweaknesses of the study by Moseley et  al.,50 which included the \nuse of a nonvalidated outcome measure and the lack of gener -\nalizability of their results. This study also showed no difference \namong the three groups in WOMAC or Short Form (SF)-36 \nscores at 2 years after surgery. Dervin et al.51 studied the ability \nof two groups of surgeons to independently predict the outcome \nof arthroscopic débridement based on clinical symptoms, signs, \nand plain radiography. A total of 126 patients were followed for \n2 years subsequent to failure of medical management and \narthroscopic débridement. Of these, 56 patients (44%) reported \na clinically important reduction in pain on the WOMAC pain \nscale. Furthermore, the investigators found that physicians cor-\nrectly predicted outcome only 59% or less of the time.\n1\nArthroscopic surgery is not recommended in patients with \ndocumented knee OA. Expert opinion suggests that arthroscopy \nshould be considered only in cases where mechanical symptoms \nrather than pain are the chief complaint.\n52\nOsteotomy\nAn osteotomy is a bone realignment procedure for unicompart-\nmental arthritis of the knee. The biomechanical principle of \nosteotomy is to redistribute the weight-bearing forces from the \nworn to the unworn compartment of the knee to relieve pain \nand slow disease progression.\n53–58 The most frequently seen defor-\nmity is varus alignment due to MCOA, with isolated lateral \ncompartment OA one-eighth as common as isolated MCOA. \nThe majority of osteotomies are performed on the proximal \ntibia to treat MCOA. Biopsy and second-look arthroscopic and \nother open procedures have shown that there is regrowth of \nfibrocartilage in the worn medial compartment with a predilec-\ntion for the ulcerated regions of wear in the weight-bearing \nportion of the medial femoral condyle.\n59–62 Box 104.1 outlines \nthe indications for an osteotomy.\nMedial compartment osteoarthritis.  Both medial opening \nwedge high tibial osteotomy (HTO) and lateral closing wedge \nHTO have been used to successfully treat MCOA (Fig. 104.4). \nBOX 104.1 Indications for an Osteotomy\nMalalignment + Arthrosis\nMalalignment + Instability\nMalalignment + Arthrosis + Instability\nMalalignment + Meniscal/Cartilage Transplant ± Instability\nPreoperative mechanical axis\nProximal cut\nPostoperative mechanical axis\nDistal cut\nFibula migrates\nlaterally\nPreoperative mechanical axis Postoperative mechanical axis\nJoint line\nAB\nFig. 104.4 Basic principles of opening wedge (A) and closing wedge (B) high tibial osteotomies. \nDescargado para juan camilo sarmiento (z0500754a@saludcastillayleon.es) en Government of Castile and Leon Ministry of Health de ClinicalKey.es por Elsevier en \njunio 02, 2026. Para uso personal exclusivamente. No se permiten otros usos sin autorización. Copyright ©2026. Elsevier Inc. Todos los derechos reservados."
    },
    {
      "pageNumber": 7,
      "text": "1282 SECTION 7 Knee\ninstability. In such cases, the condition must be corrected to \ncreate a stable joint before ligamentous reconstruction, and a \ncombined ligamentous and bony procedure should be considered \nto decrease the risk of graft failure.\n5,8,74 Normally the posterior \ntibial slope is 10 degrees ± 3 degrees.27 A posterior tibial slope \ngreater than 13 degrees results in anterior tibial translation and \naltered joint biomechanics, as well as meniscal load sharing, \nleading to increased chondral wear. Similarly, a posterior tibial \nslope of less than 7 degrees (relative decreased slope) is also \nconsidered abnormal and leads to posterior translation of the \ntibia, which may have a similar outcome.\n75 When these condi-\ntions are symptomatic, they should be addressed with an oste -\notomy to improve the bony stability. Osteotomies for sagittal \nplane deformities are usually approached anteriorly with either \nan anterior closing wedge osteotomy for increased tibial slope \nor an opening wedge osteotomy for decreased slope.\n76\nCombined instability and pain.  Patients with chronic liga -\nmentous deficiency may present with pain, instability, or both. \nPatients most commonly have chronic ACL deficiency. However, \nposterior cruciate ligament and posterolateral corner insufficiency \nmay also be present. It has been shown that in patients with \ninstability and malalignment, soft tissue ligamentous reconstruc-\ntion may fail because of the malalignment.\n5,74 Therefore an oste-\notomy to correct the malalignment followed by simultaneous \nor staged ligamentous reconstruction should be considered.\n8\nIn patients for whom the primary symptom is instability with \nmild or moderate medial compartment degeneration, an oste -\notomy alone may not prove beneficial. Although ligament recon-\nstruction alone has been shown to be successful,9,77,78 it does not \naddress the malalignment, predictably alleviate any symptoms \nof pain, or offer any chondroprotection to the damaged medial \ncompartment. In these patients, an osteotomy to address pain \ncombined with a simultaneous or staged soft tissue procedure \nto address ligament deficiency should be considered.\nIn patients presenting with chronic ACL deficiency, treat -\nment options include lateral closing wedge osteotomy or com -\nbined HTO and ACL reconstruction. A lateral closing wedge \nosteotomy favorably decreases the tibial slope, which helps to \nimprove instability related to ACL deficiency. A medial opening \nwedge osteotomy tends to change tibial slope in an unfavorable \nLateral compartment osteoarthritis.  Lateral compartment \nOA can be caused by pathology on the femoral or tibial side of \nthe knee. The osteotomy should be performed at the site of the \ncause of the deformity.\nProximal tibial osteotomies. The results of proximal tibial \nvarus osteotomies have not equaled those of proximal tibial valgus \nosteotomies. A concern remains that proximal tibial osteoto-\nmies for lateral compartment OA will cause joint-line obliquity \ngreater than 10 degrees, leading to lateral subluxation of the \ntibia. Another concern is that medial collateral ligament (MCL) \nlaxity occurs if the wedge is taken above the MCL insertion. \nHowever, a role still exists for proximal tibial osteotomy in the \nvalgus knee. This role includes small corrections of 12 degrees \nor less that avoid excessive joint line obliquity in persons with \nposttraumatic OA for whom the deformity is primarily at or \nbelow the joint. If the deformity is primarily in the femur or the \ncorrection is greater than 12 degrees, a distal femoral osteotomy \nshould be considered.\n72,73\nDistal femoral osteotomies. A distal femoral varus osteotomy \nis an appropriate procedure for patients with valgus deformity \nof the femur, such as a hypoplastic lateral femoral condyle, or \nif the required correction is greater than 12 degrees.\n23 Again, \nthis procedure can be a medial closing wedge or a lateral opening \nwedge osteotomy. The advantages and disadvantages of each \nprocedure are similar to those listed for opening and closing \nwedge proximal tibial osteotomies in persons with MCOA (see \nTable 104.2). One additional advantage of a lateral opening wedge \ndistal femoral osteotomy is that the correction can be tailored \nto the desired amount of varus. On the other hand, the medial \nclosing wedge technique using a 90-degree blade plate typically \nresults in a tibiofemoral angle correction of 0 degrees and a \nmechanical axis correction of 6 degrees varus.\n72 Whether tailor-\ning the correction with a lateral opening wedge technique is \nsuperior to using the medial closing wedge technique with regard \nto long-term outcome has yet to be determined.\nKnee instability. Knee instability can be due to both bony \nand soft tissue factors. Ligamentous causes are the most common. \nHowever, altered tibial slope in the sagittal plane occurring in \nisolation as a result of a tibial physeal arrest or in combination \nwith ligamentous insufficiency can also cause anteroposterior \nAdvantages Disadvantages\nMedial opening wedge The procedure is technically easier to perform \n(requiring just one bone cut).\nIt provides the ability to achieve a predictable \ncorrection in coronal and sagittal planes.\nIt can be combined with other procedures such as \nligamentous reconstruction with relative ease.\nIt restores bone stock.\nHealing in distraction leads to more potential problems with delayed \nand nonunion.\nThe tibial slope may be difficult to maintain.\nLateral closing wedge Healing in compression leads to fewer problems with \ndelayed and nonunion.\nIt provides favorable alterations in the tibial slope to \ntreat chronic anterior cruciate ligament deficiency.\nThe procedure is technically more difficult for inexperienced surgeons.\n• Peroneal nerve\n• Proximal tibiofibular joint\nIt decreases bone stock.\nIt makes future total knee arthroplasty more technically challenging.\nTABLE 104.2 Medial Opening Wedge Versus Lateral Closing Wedge High Tibial Osteotomy\nDescargado para juan camilo sarmiento (z0500754a@saludcastillayleon.es) en Government of Castile and Leon Ministry of Health de ClinicalKey.es por Elsevier en \njunio 02, 2026. Para uso personal exclusivamente. No se permiten otros usos sin autorización. Copyright ©2026. Elsevier Inc. Todos los derechos reservados."
    },
    {
      "pageNumber": 8,
      "text": "1283CHAPTER 104 Knee Arthritis\nactivity after surgery (data for a total of 35 knees were reviewed). \nAt a mean follow-up of 9.7 years (range, 5 to 16 years), 75% had \nreturned to manual work at the same level as before surgery, 60% \nhad returned to the same level of participation in sports, and \n30% were participating in sports at a lower level. T en percent \nwere unable to return to their sport. The authors acknowledge \nthat revision for polyethylene wear remains the main concern.\n93 \nIn a biomechanical study, Kuster98 previously demonstrated that \nrunning and jumping produces surface loads that exceed the \nlimits of polyethylene resistance. The general recommendation \nfor return to sport after an arthroplasty is low-impact activities \nsuch as cycling, bowling, swimming, scuba, golf, skating, cross-\ncountry skiing, weight lifting, dancing, and walking.\n99\nDECISION-MAKING PRINCIPLES\nManagement of patients with knee OA should be individualized. \nPhysiologic rather than chronologic age should be considered, \nalong with the patient’s goals and expectations. Patient education \nis paramount to the successful management of these patients. \nFig. 104.5 outlines the treatment algorithm for patients present-\ning with knee OA. Management always begins with nonoperative \ntreatment and progresses from less invasive to more invasive \noptions (see Fig. 104.3).\nMedial Compartment Osteoarthritis\nSeveral factors must be considered in deciding on the best surgi-\ncal treatment for patients with isolated MCOA of the knee for \nwhom conservative management has failed. Table 104.3 out -\nlines the indications for HTO versus UKA versus TKA in these  \npatients.\ndirection; therefore combined procedures should be consid -\nered.\n53,55,79 Previous studies have described combined HTO and \nACL reconstruction as simultaneous or staged procedures, with \nthe osteotomy usually performed first.\n74,80 Simultaneous medial \nopening wedge HTO and ACL reconstruction allows for biplanar \ncorrection of the knee deformity with restoration of ligamentous \nsupport in one operation and results in improvements in both \nbony and soft tissue support, which in theory leads to improved \noverall knee joint function.\n6,81–83\nReturn to sport after an osteotomy.  The true benefit of an \nosteotomy is that is allows unrestricted activity while preserving \nthe knee joint. Multiple studies have shown that HTO affords \nyoung, active patients with OA the ability to return to recreational \nsports and maintain an active lifestyle.\n84,85 Van Raaij et a l.86 found \nthat HTO postpones primary total knee arthroplasty (TKA) for \na median of 7 years in this group of patients.\nPatient satisfaction after high tibial osteotomy. With careful \npatient selection, satisfaction after HTO is very high. Hui et al.87 \nshowed that at a mean follow-up of 12 years, 85% of a cohort \nof 397 patients who underwent lateral closing wedge HTO were \nenthusiastic or satisfied and 84% would have the same surgery \nagain. Similarly, at a mean of 6.5 years after surgery, Tang and \nHenderson\n88 reported patient satisfaction of 76%, with 90% of \npatients saying they would choose the same surgery again.\nArthroplasty\nMedial compartment osteoarthritis. For many years, unicom-\npartmental knee arthroplasty (UKA) has been performed to treat \nisolated MCOA. The potential benefits of UKA compared with \nTKA are lower perioperative morbidity, less blood loss, main -\ntenance of normal knee kinematics, and quicker patient reha -\nbilitation and recovery.\n89 Controversies remain regarding a fixed \nbearing versus mobile bearing implant design, but both have \nshown good long-term success.\n90–92 However, concern remains \nregarding the durability of UKA in younger patients. 93\nTricompartmental osteoarthritis. In patients presenting with \nsevere tricompartmental osteoarthritis, the gold standard is a \nTKA. This procedure offers long-term, predictable pain relief. \nTKA for symptoms other than pain, such as stiffness, swelling, or \ninstability, has unpredictable outcomes and is not recommended.\n94\nCombined instability and pain. Historically, ACL insufficiency \nhas been a contraindication to UKA because of concerns relating \nto increased anterior tibial translation and altered knee biome -\nchanics with subsequent increased lateral compartment arthrosis \nand polyethylene wear resulting from posterior loading of the \nimplant and ultimate prosthesis failure. Recently combined UKA \nusing the Oxford prosthesis (Biomet, Oxford, UK) and ACL \nreconstruction has been performed to address both instability \nand pain related to MCOA. However, controversy remains regard-\ning implant survival in this subgroup.\n95,96 Lateral UKA is con-\ntraindicated in patients with ACL insufficiency because of \nincreased lateral compared with medial compartment mobility, \nwhich leads to even more abnormal contact pressures and a \npotentially higher rate of failure.\n97\nReturn to sport after arthroplasty.  Parratte et al.93 reviewed \ndata for 31 patients who underwent UKA at a mean age of 46 \nyears (range, 41 to 49 years) and who were allowed unrestricted \nHTO UKA TKR\nAgea ≤65 years ≥55 years ≥65 years\nActivity level High Low Low\nBody mass index Any <30 <30\nMalalignment 5–20 degrees 0–5 degrees Any\nAP instability Any Noneb Anyc\nML instability ≤Grade II None Anyc\nROM Arc ≥120 degrees Arc ≥90 degrees Any\nMCOA Any Any Any\nPFOA ≤Grade IId ≤Grade IId Any\nLCOA Any Any Any\nTABLE 104.3 Indications for Surgery in \nPatients With Medial Compartment \nOsteoarthritis of the Knee\naPhysiologic age should be considered here.\nbLong-term results of combined ACL reconstruction and UKA have \nnot been established.\ncIncreasing instability requires increased component constraint.\ndFor MCOA, the patient may have up to grade II PFOA if no \npatellofemoral symptoms are present.\nAP, Anteroposterior; HTO, high tibial osteotomy; LCOA, lateral \ncompartment osteoarthritis; MCOA, medial compartment \nosteoarthritis; ML, mediolateral instability; PFOA, patellofemoral \nosteoarthritis; ROM, range of motion; TKR, total knee replacement; \nUKA, unicompartmental knee arthroplasty.\nDescargado para juan camilo sarmiento (z0500754a@saludcastillayleon.es) en Government of Castile and Leon Ministry of Health de ClinicalKey.es por Elsevier en \njunio 02, 2026. Para uso personal exclusivamente. No se permiten otros usos sin autorización. Copyright ©2026. Elsevier Inc. Todos los derechos reservados."
    },
    {
      "pageNumber": 9,
      "text": "1284 SECTION 7 Knee\nLateral Compartment Osteoarthritis\nIn general, lateral compartment OA is better tolerated than MCOA. \nThe treatment algorithm for patients with symptomatic lateral \ncompartment OA of the knee for whom conservative manage -\nment has failed is shown in Fig. 104.6. The lateral compartment \nUKA procedure remains controversial and is not recommended \nuntil longer-term results are reported.\nChronic Anterior Cruciate  \nLigamentous Insufficiency\nFig. 104.7 outlines the treatment algorithm for patients who \npresent with symptomatic instability and pain caused by chronic \nACL insufficiency. Use of UKA in patients with chronic ACL \ninsufficiency with or without combined ACL reconstruction is \ncontroversial and is not recommended.\nKnee osteoarthritis\nRest and activity modification\nWeight loss\nPhysical therapy\nBracing\nAnalgesics and NSAIDs\nYes\nYes\nYes\nNo\nNo\nNo\nAcute\nflare-up?\nHelpful?\nTrue\nmechanical\nsymptoms?\nCorticosteroid\ninjection Continue\nnonoperative\nmanagement\nFlare-\nup\nsettled\nConsider\narthroscopy\nHigh tibial\nosteotomy\nDistal femoral\nosteotomy\nUnicompartmental\narthroplasty\nTotal knee\narthroplasty\nHigh-demand\nmedial OA\nHigh-demand\nlateral OA\nLower demand\nunicompartmental OA\nTricompartmental\nOA\nFig. 104.5 A treatment algorithm for patients with knee osteoarthritis (OA). NSAIDs, Nonsteroidal antiinflam-\nmatory drugs. \nLateral compartment\nosteoarthritis\nDeformity on\ntibial side\nDeformity on\nfemoral side Age >65\nCorrection ≤12° Correction >12°\nProximal tibial\nvarus osteotomy\nDistal femoral\nvarus osteotomy\nMedial\nclosing\nwedge\nLateral\nopening\nwedge\nMedial\nclosing\nwedge\nLateral\nopening\nwedge\nTotal knee\narthroplasty\nFig. 104.6 A treatment algorithm for patients with lateral compartment \nknee osteoarthritis. \nChronic ACL insufficiency\nPain Instability Both\nADLs SportCheck alignment\nCheck alignmentVarus\nVarus\nNeutral Valgus\nValgus\nHTO DFOPotential\nrole for\narthroscopy\nSymmetrical Asymmetrical\nACLR Combined\nHTO/ACLR\nCombined\nDFO/ACLR\nFig. 104.7 A treatment algorithm for patients with chronic anterior cruci-\nate ligament (ACL) insufficiency and osteoarthritis. ACLR, Anterior cruciate \nligament reconstruction; ADLs, activities of daily living; DFO, distal femoral \nosteotomy; HTO, high tibial osteotomy. \n Authors’ Preferred Technique\nOur preferred technique for physiologically young patients with medial com -\npartment osteoarthritis who place a high demand on their knees is a medial \nopening wedge high tibial osteotomy. We use a modification of the technique \npreviously described by Puddu and Franco. 100 Preoperative planning is critical \nto osteotomy surgery and begins with a determination of limb alignment in \nboth the coronal and sagittal planes.\nMedial Collateral Osteoarthritis\nDescargado para juan camilo sarmiento (z0500754a@saludcastillayleon.es) en Government of Castile and Leon Ministry of Health de ClinicalKey.es por Elsevier en \njunio 02, 2026. Para uso personal exclusivamente. No se permiten otros usos sin autorización. Copyright ©2026. Elsevier Inc. Todos los derechos reservados."
    },
    {
      "pageNumber": 10,
      "text": "1285CHAPTER 104 Knee Arthritis\n Authors’ Preferred Technique\nPreoperative Planning\n1. Obtain the following radiographs of both limbs: standing anteroposterior (AP)  \nin full extension, standing 30-degree posteroanterior, lateral, skyline, and \nstanding hip to ankle.\n•\n Assess lateral and patellofemoral osteoarthritis (OA).\n• Measure patellar height.\n• Measure the posterior tibial slope.\n2. Plan the osteotomy. We typically use the technique previously described by \nDugdale et al. (Fig. 104.8).101\n• Measure the width of the tibial plateau.\n• Determine the correction point at 62.5% across the plateau from the medial  \nedge. This point lies slightly lateral to the tip of the lateral tibial spine and \nequates to 3 to 5 degrees of mechanical valgus (see Fig. 104.8A).\n•\n Draw a line from the center of the femoral head to the 62.5% correction \npoint (ȧ) and another line from the center of the ankle to this point (ḃ) (see \nFig. 104.8B).\n• Draw the intended osteotomy from the junction of the proximal tibial \nmetadiaphysis (~4  cm from the top of the medial tibial plateau) to the \ntop of the fibular head (e ˙ ) and measure the length of the osteotomy (see  \nFig. 104.8C).\n• Transpose the intended osteotomy line (e ˙  → ë) over the top of line ḃ (see \nFig. 104.8D).\n• Draw a line (l) perpendicular to the top of line ë across to line ȧ. Measure \nthe length of this line. This line serves as the base of an isosceles triangle \nand is the intended wedge size of the osteotomy (see Fig. 104.8E).\nDiagnostic Arthroscopy\n1.\n Examine the lateral and patellofemoral compartments.\n• If Ahlbäck grade II or III degeneration is present in the lateral compart -\nment, consider correcting the weight-bearing line to 50% the distance \nacross the width of the tibial plateau rather than to the 62.5% point.\n•\n If Ahlbäck grade IV degeneration is present in the lateral compartment, \nabandon the osteotomy and consider total knee arthroplasty at a later \ndate.\n•\n If Ahlbäck grade IV degeneration is present in the patellofemoral joint, \nconsider a concomitant tibial tubercle osteotomy (TTO).\n2. Perform any meniscal work or débridement as required.\n3. A 5-cm longitudinal incision is made starting 1  cm distal to the medial joint \nline midway between the tibial tubercle and the posteromedial border of \nthe tibia (Fig. 104.9A).\nMedial Opening Wedge High Tibial Osteotomy\nContinued\nA\nDE\nBC\n62.5%\n12.5mm\nFig. 104.8  The trigonometric method for planning the osteotomy size for an opening wedge high tibial \nosteotomy. \nDescargado para juan camilo sarmiento (z0500754a@saludcastillayleon.es) en Government of Castile and Leon Ministry of Health de ClinicalKey.es por Elsevier en \njunio 02, 2026. Para uso personal exclusivamente. No se permiten otros usos sin autorización. Copyright ©2026. Elsevier Inc. Todos los derechos reservados."
    },
    {
      "pageNumber": 11,
      "text": "1286 SECTION 7 Knee\nAuthors’ Preferred Technique—cont'd\nMedial Opening Wedge High Tibial Osteotomy—cont’d\nA\nB\nD\nC\nE\nF\nLarge osteotome placed \nbeneath pin matching\nposterior tibial slope Oscillating saw cutting\ntibial cortex in same plane\nwith posterior tibial slope\nAnterior border of SMCL\nGuide pin placement\nMeta-diaphysisPatella\nPatellar tendon\nCobb elevator\nGastrocnemius\nFemur\nSMCL\nTibial tuberosity\nPes anserine \n released\nTibia\nSMCL Pes anserine\nPes anserine \n released\nSartorial\nfasciaMedial joint line\n1 cm\nTubercle\n5 cm\nFig. 104.9 A large osteotome is placed beneath the pin and adjusted so that it is in line with the posterior \ntibial slope on an anteroposterior image of the knee. With the knee and the osteotome in plane with the \nposterior tibial slope on the fluoroscopic image of the knee, the plane of the osteotomy will match the \nposterior tibial slope of the patient. This step is critical. SMCL, Superficial medial collateral ligament. \nDescargado para juan camilo sarmiento (z0500754a@saludcastillayleon.es) en Government of Castile and Leon Ministry of Health de ClinicalKey.es por Elsevier en \njunio 02, 2026. Para uso personal exclusivamente. No se permiten otros usos sin autorización. Copyright ©2026. Elsevier Inc. Todos los derechos reservados."
    },
    {
      "pageNumber": 12,
      "text": "1287CHAPTER 104 Knee Arthritis\nAuthors’ Preferred Technique—cont'd\nMedial Opening Wedge High Tibial Osteotomy—cont’d\nSmall, thin flexible\nosteotome advancing to \nlateral tibial cortex\nLarge osteotome \nplaced deeper to widen\nthe wedge cut\nOsteotome jack blades\ninserted 2/3 across\nosteotomy\nOsteotomy wedge trial\ninserted into posterior \naspect of osteotomy \nto desired correction\n3 locking cancellous screws\nContour lock plate\n3 locking cortical screws\nK\nG\nIJ\nH\nFig. 104.9, cont’d\nContinued\nDescargado para juan camilo sarmiento (z0500754a@saludcastillayleon.es) en Government of Castile and Leon Ministry of Health de ClinicalKey.es por Elsevier en \njunio 02, 2026. Para uso personal exclusivamente. No se permiten otros usos sin autorización. Copyright ©2026. Elsevier Inc. Todos los derechos reservados."
    },
    {
      "pageNumber": 13,
      "text": "1288 SECTION 7 Knee\nAuthors’ Preferred Technique—cont'd\nMedial Opening Wedge High Tibial Osteotomy—cont’d\n4. Expose the sartorial fascia and open it at the top of the pes anserine. Retract \nthe pes tendons distally. Sharply release the pes from its insertion onto the \ntibia to expose the superficial medial collateral ligament (MCL) (see Fig. 104.9B).\n5. Identify the posteromedial border of the tibia and, using electrocautery, \nmake a 1- to 1.5-cm longitudinal incision along this border in line with the \nfibers of the superficial MCL.\n6.\n Using a Cobb elevator, bluntly lift the gastrocnemius off the posterior aspect  \nof the tibia, making sure to stay on the bone (see Fig. 104.9C).\n7. Insert a finger into this interval to ensure that the dissection has been carried  \nout across the entire width of the tibia and insert a blunt retractor to protect \nthe neurovascular structures.\n8.\n Next, identify the medial border of the patellar tendon and the interval \nbetween the tibia and patellar tendon bursa. Place a retractor into this \ninterval.\n9.\n Obtain an AP image of the knee in line with the posterior tibial slope (at \napproximately 10 degrees of knee flexion).\n10. Place a guide pin along the anterior border of the superficial MCL at the \njunction of the metadiaphysis of the proximal tibia. Under fluoroscopy, direct \nthe pin toward the top of the fibular head to a point approximately 1  cm \nbelow the lateral joint line (see Fig. 109.4D).\n11. Place a large osteotome beneath the pin and adjust it so that it is in line \nwith the posterior tibial slope on an AP image of the knee. With the knee \nand the osteotome in plane with the posterior tibial slope on the fluoroscopic \nimage of the knee, the plane of the osteotomy will match the posterior tibial \nslope of the patient. This step is critical (see Fig. 104.9E).\n12.\n Mark the position of the osteotome with a marking pen followed by elec -\ntrocautery (see Fig. 104.9D). If a TTO is required, mark the osteotomy line \n1 cm short of the tibial tubercle (see the section titled “Concomitant Tibial \nTubercle Osteotomy” in this box for details).\n13. Cut the tibial cortex with a small oscillating saw blade between the tibial \ntubercle and the posteromedial tibial border (see Fig. 104.9E). It is imperative \nthat the angle of the saw blade be in plane with the posterior tibial slope, \nsimilar to the osteotome in step 11. The osteotomy is made below the guide \npin to avoid proximal migration of the osteotomy into the joint.\n14.\n The osteotomy is advanced toward the lateral tibial cortex using small, thin,  \nflexible osteotomes (see Fig. 104.9F).\n15. G raduated solid osteotomes are then used, starting with the broadest, which \nis usually advanced to two-thirds the width of the osteotomy. A narrow \nosteotome is then used along the posterior tibial cortex and is advanced to \napproximately 1 cm from the lateral tibial cortex under fluoroscopic guidance.  \nAgain, it is critical for the plane of the osteotomy to mimic the posterior \ntibial slope (see Fig. 104.9G).\n16.\n Check the mobility of the osteotomy by applying a valgus force across the \nosteotomy. It should open easily. If it does not open easily, step 15 should \nbe repeated until the osteotomy opens without difficulty to the desired \nwedge size.\n17.\n Insert both blades of an osteotome jack approximately two-thirds across \nthe osteotomy and gradually open the jack to the desired correction (see \nFig. 104.9H).\n18.\n At this point, check that the osteotomy is trapezoid in shape (i.e., narrower \nanteriorly and wider posteriorly because the tibia is a triangular-shaped \nbone). A rectangular-shaped osteotomy indicates that the posterior tibial \nslope has been altered.\n19.\n Insert the osteotomy wedge trial to the desired correction and confirm that \nthe limb is in valgus alignment (see Fig. 104.9I).\n20. With the wedge trial holding the osteotomy open, insert the plate into the \nosteotomy site. Bend the plate as required to fit the shape of the tibia. Once \nthe plate has been inserted, remove the wedge trial.\n21.\n Secure the plate with three locking cancellous screws above and three \nlocking cortical screws below. The screws should be directed away from \nthe osteotomy (see Fig. 104.9J).\n22.\n Mix corticocancellous allograft bone chips with 1  g of vancomycin powder. \nInsert and pack the mixture into the osteotomy with a bone tamp. Note that \nbone grafting is optional for corrections of 7.5  mm or less (Fig. 104.10).\n23. Repair the pes anserine over the top of the plate.\n24. Insert a drain to exit separately from the incision.\n25. Close the skin over the top of the drain.\n26. Apply a hinged knee brace locked in full extension.\nConcomitant Tibial Tubercle Osteotomy\nIndications for a concomitant TTO are (1) large corrections greater than 12.5 mm  \nand (2) severe patellofemoral osteoarthritis.\n1.\n If a TTO is required, mark the osteotomy line 1  cm short of the tibial tubercle \nin step 12. It is important that the thickness of the TTO be 1  cm proximally \nto avoid fracture.\n2. From this point, mark a line exiting the anterior tibial cortex approximately \n3 cm distally using electrocautery. For a larger correction, the length of the \nTTO should be extended to allow enough room for adequate fixation because \nthe tubercle will translate superomedially with the opening of the osteotomy.\n3.\n After the osteotomy cut has been made, make a flat TTO cut along the previ-\nously marked line with the small oscillating saw from medial to lateral. It is \nimportant that the cut be flat to allow appropriate translation of the tubercle \nwhen the osteotomy is distracted.\n4.\n Proceed with steps 14 to 22 as previously outlined.\n5. Just before closure (step 23), secure the TTO with one or two 4.5-mm cortical  \nscrews from an anterior-to-posterior direction. It is important to countersink \nthese screws to avoid screw prominence anteriorly.\nAB\nFig. 104.10 Anteroposterior (A) and lateral (B) radiographs demonstrat-\ning a completed medial opening wedge high tibial osteotomy with a \ntibial tubercle osteotomy. \nDescargado para juan camilo sarmiento (z0500754a@saludcastillayleon.es) en Government of Castile and Leon Ministry of Health de ClinicalKey.es por Elsevier en \njunio 02, 2026. Para uso personal exclusivamente. No se permiten otros usos sin autorización. Copyright ©2026. Elsevier Inc. Todos los derechos reservados."
    },
    {
      "pageNumber": 14,
      "text": "1289CHAPTER 104 Knee Arthritis\nsurgery. Most patients are able to return to the sport they previ-\nously played. However, some patients may never be able to return \nat the same level. 84,85\nRESULTS\nThe mid- and long-term outcomes of HTO for MCOA of the \nknee have been well established and are shown in Table \n104.5.\n87,88,103–108 Fewer, smaller studies reporting the outcomes \nof distal femoral osteotomies for lateral compartment OA of the \nknee are available (Table 104.6).\n109–118 Lateral compartment OA \nis less common than medial compartment disease; frequently \npatients with lateral compartment OA have an inflammatory \narthropathy that precludes realignment procedures.\nAlthough numerous large long-term studies of closing wedge \nproximal tibia and distal femoral osteotomies have been per -\nformed, fewer studies of the opening wedge osteotomy exist. \nHernigou et al.108 published the largest study on medial opening \nwedge HTO in 1987 with a mean follow-up of 11.5 years. Out-\ncomes of lateral opening wedge distal femoral osteotomies have \nbeen reported in small case series with short-term follow-up \nperiods.\n109,110\nComplications\nComplications of HTO can be categorized as intraoperative, \nearly postoperative, or late postoperative. Table 104.7\n71,119–121 \noutlines the most common complications and their management. \nComplications after a distal femoral osteotomy are very similar \nto those that occur after a proximal tibial osteotomy.\nPOSTOPERATIVE MANAGEMENT\nThe most important aspect of rehabilitation after an HTO is \nROM. Early postoperative knee ROM exercises promote healing \nand articular cartilage nourishment as well as lower limb neu-\nromuscular function. Normal weight bearing is encouraged \nas soon as possible to help with bone turnover and healing.\n102 \nWith the advent of locking-plate technology, partial weight \nbearing can commence at 2 weeks after surgery; full weight \nbearing is usually achieved by 6 weeks. Several recent studies \nhave shown that early weight bearing with locking plates does \nnot negatively affect limb alignment, loss of correction, and  \ndelayed/nonunion.\n63,64\nTable 104.4 outlines our rehabilitation protocol after uncom-\nplicated medial opening wedge HTO using a locking plate. Each \nphase in this regimen builds on the previous one, and every \npatient should be treated on an individual basis based on the \ntype of surgery he or she underwent. For example, if concomitant \nprocedures such as ligament reconstruction, microfracture, or \nmeniscal transplant are performed, the rehabilitation program \nshould be altered with these procedures in mind. If a nonlock -\ning plate is used, the approximate time lines must be adjusted \naccordingly.\nReturn to sport and activity is permitted when radiographic \nand clinical evidence shows bone healing and the patient has \nregained muscle bulk and control of the newly aligned limb. \nTiming of return to play (RTP) depends on the individual patient, \nhis or her type of surgery, and his or her sport or activity. RTP \ncan occur in as few as 6 months or as many as 18 months after \nPhase Approximate Time Line Guidelines Restrictions\n1\n(Immediate \npostoperative)\nDay of surgery to 2 weeks Manage pain and swelling\nStart ROM exercises (may come out of brace)\nActivate quadriceps\nBrace is worn full time except during \nexercises (locked in extension)\nFeather/touch weight bearing\n2\n(Early postoperative)\n2–6 weeks Regain full ROM (especially extension)\nGait retraining → progress to WBAT\nStationary bike with low resistance\nCore/proximal muscle/quadriceps strengthening\nBrace is worn full time except during \nexercises (fully unlocked)\n3\n(Muscle strengthening \nand control)\n6 weeks–3 months Normal gait—no limp\nContinue strengthening\nStretching and flexibility\nIncrease cardiovascular fitness with low-impact \nexercise\nBalance and proprioception exercises (e.g., \nwobble board)\nPool work (e.g., water running)\nBrace is off\nLow-impact activities\n4\n(Neuromuscular \nretraining and return \nto normal function)\n3–6 months Begin neuromuscular training exercises\nContinue strengthening\nProgress to resistance on gym equipment and \nmaintain cardiovascular fitness\nMay ride normal bicycle\n5\n(Return to sport and \nactivities)\n9–12 months Progress to neuromuscular training exercises\nMay progress to higher-impact activities\nGradual return to all activities, including sports\nNo restrictions\nTABLE 104.4 Postoperative Rehabilitation Guidelines After a Medial Opening Wedge High \nTibial Osteotomy\nROM, Range of motion; WBAT, weight bearing as tolerated.\nDescargado para juan camilo sarmiento (z0500754a@saludcastillayleon.es) en Government of Castile and Leon Ministry of Health de ClinicalKey.es por Elsevier en \njunio 02, 2026. Para uso personal exclusivamente. No se permiten otros usos sin autorización. Copyright ©2026. Elsevier Inc. Todos los derechos reservados."
    },
    {
      "pageNumber": 15,
      "text": "1290 SECTION 7 Knee\nStudy Year No.\nMean Follow-Up \n(Years) (Range)\nMean Age \n(Years) Technique Outcomes\nHui et al.87 2011 455 patients 12 (1–19) 50 LCW 95% survival 5 years\n79% survival 10 years\n56% survival 15 years\nSaragaglia et al.103 2011 110 patients \n(124 knees)\n10.4 (8–14) 53.3 MOW 88% survival 5 years\n74% survival 10 years\nDeMeo et al.104 2010 20 patients 8.3 (2–14) 49.4 MOW 70% survival 8 years\nAkizuki et al.105 2008 132 patients 16 (16–20) 63 LCW 98% survival 10 years\n90% survival 15 years\nGstöttner et al.106 2008 111 patients \n(132 knees)\n12 (1–25) 54 LCW 80% survival 10 years\n66% survival 15 years\nTang and Henderson\n88 2005 67 knees 6.5 (1–21) 49 LCW 75% survival 10 years\n67% survival 15 years\nNaudie et al.107 2004 85 patients \n(106 knees)\n14 (10–22) 55 LCW 95% survival 5 years\n80% survival 10 years\n65% survival 15 years\nHernigou et al.108 1987 184 patients \n(250 knees)\n11.5 (10–13) 60.3 MOW 90% good/excellent 5 years\n45% good/excellent 10 years\nTABLE 104.5 Long-Term Outcomes of a High Tibial Osteotomy for Medial Compartment \nOsteoarthritis\nLCW, Lateral compartment wedge; MOW, medial opening wedge.\nStudy Year No.\nMean Follow-Up \n(Years) (Range)\nMean Age \n(Years) Technique Outcomes\nSternheim et al.109 2011 41 patients \n(45 knees)\n13.3 (3–25) 46.2 MCW 90% survival 10 years\n79% survival 15 years\n21.5% survival 20 years\nPuddu et al.110 2009 30 patients – (4–12) 52 LOW 82% good/excellent\nDas et al.111 2008 12 patients 74 monthsa (51–89) 52 LOW 58% good/excellent\nBackstein et al.112 2007 38 patients \n(40 knees)\n10 (3–20) 44 MCW 82% survival 10 years\n45% survival 15 years\nWang and Hsu\n113 2006 30 patients 8 (5–14) 53 MCW 87% survival 10 years\nGross and Hutchison114 2000 20 patients \n(21 knees)\n11 (5–20) 56 MCW 83% survival 4 years\n64% survival 10 years\nMarti et al.115 2000 15 patients – (1–14) 59 MCW 73% good results\nFinkelstein et al.116 1996 20 patients \n(21 knees)\n11 (8–20) 59 MCW 64% survival 10 years\nHealy et al.117 1988 21 patients \n(23 knees)\n4 (2–9) 56 MCW 83% good/excellent\nMcDermott et al.118 1988 24 patients 4 (2–11.5) 52 MCW 92% good results (most \nimprovement in pain)\nTABLE 104.6 Long-Term Outcomes of a High Tibial Osteotomy for Lateral Compartment \nOsteoarthritis\naTelephone follow-up of functional Hospital for Special Surgery and Lysholm score.\nLOW, Lateral opening wedge; MCW, medial compartment wedge.\nSUMMARY\nKnee OA is a common condition encountered by all physicians. \nArthritis in an athlete can be particularly difficult to treat, given \nthe high demands that athletes place on their bodies. Because \nopening wedge osteotomies have emerged as the preferred \nmethod of surgical management, future studies should focus \non determining the long-term outcomes in larger numbers of \npatients. Additionally, better defining the success of early weight \nbearing after locking-plate HTO will be vital.\nConservative management should be the first line of therapy. \nSurgical intervention is considered in patients who have exhausted \nconservative therapies. Joint-preserving osteotomy procedures \nare recommended in active persons with unicompartmental OA. \nDescargado para juan camilo sarmiento (z0500754a@saludcastillayleon.es) en Government of Castile and Leon Ministry of Health de ClinicalKey.es por Elsevier en \njunio 02, 2026. Para uso personal exclusivamente. No se permiten otros usos sin autorización. Copyright ©2026. Elsevier Inc. Todos los derechos reservados."
    },
    {
      "pageNumber": 16,
      "text": "1291CHAPTER 104 Knee Arthritis\n(MRI) in osteoarthritis of the knee. J Bone Joint Surg Am. \n2003;85A(1):4–9.\nLevel of Evidence:\nI\nSummary:\nMeniscal tears are highly prevalent in both asymptomatic and \nclinically osteoarthritic knees of older persons. Because \nosteoarthritic knees with a meniscal tear are not more painful \nthan those without a tear and the meniscal tears do not affect \nTKA is a successful procedure reserved for less active persons \nor those with tricompartmental arthritis.\nFor a complete list of references, go to ExpertConsult.com.\nSELECTED READINGS\nCitation:\nBhattacharyya T, Gale D, Dewire P , et al. The clinical importance of \nmeniscal tears demonstrated by magnetic resonance imaging \nComplication Osteotomy Frequency (%) Management\nIntraoperative\nIntra-articular fracture MOW 7–18.2 Determine if additional fixation required\nConsider changing weight-bearing status postoperatively\nFracture of opposite cortex MOW\nLCW\n4.3 No additional procedure required (MOW)\nAdditional fixation required (LCW)\nPeroneal nerve injury LCW 2–16 Most commonly neurapraxia—monitor and consider NCS and EMG 6 weeks \nafter surgery if no sign of improvement\nTag ends of nerve and consult plastic surgeon if patient has direct nerve injury\nVascular injury All 0.4 Gain proximal and distal control of vessel if possible\nCall vascular surgeon\nEarly Postoperative\nUndercorrection/overcorrection All — Revision osteotomy\nHematoma All 10.2 Preventable with insertion of drain\nIrrigation and débridement if associated with prolonged drainage\nInfection All 2.3–81 Antibiotic therapy\nRegular pin site care with external fixator\nVTE All 1.3–9.8 No routine prophylaxis required—encourage mobilization\nConsider prophylaxis with LMWH in high-risk patients\nProphylaxis with 6 weeks of warfarin (Coumadin) in patients with known \nhistory of VTE\nStiffness All 3 Preventable with early ROM\nPhysiotherapy\nConsider manipulation with the patient anesthetized once the osteotomy has \nunited\nConsider arthrolysis if severe\nCompartment syndrome All 2–2.6 Emergent compartment release\nLate Postoperative\nDelayed union MOW 4.3 Rule out infection\nBone graft osteotomy site\nNonunion MOW 0.7–4.4 Rule out infection\nBone graft osteotomy site\nPseudoarthrosis MOW 0.7–4.4 Rule out infection\nBone graft osteotomy site\nHardware irritation All 4.3 Implant removal\nLoss of correction All 4.4–15.2 Revision osteotomy\nFailure of fixation All 4.4–16.4 Revision osteotomy\nPatella baja All 7.6–8.8 Consider simultaneous TTO for MOWHTO corrections ≥\n12.5 mm\nEarly ROM\nTABLE 104.7 Complications Associated With High Tibial Osteotomy Surgery\nEMG, Electromyography; LCW, lateral closing wedge; LMWH, low molecular weight heparin; MOW, medial opening wedge; MOWHTO, medial \nopening wedge high tibial osteotomy; NCS, nerve conduction study; ROM, range of motion; TTO, tibial tubercle osteotomy; VTE, venous \nthromboembolism.\nData from references 71, 119, 120, and 121.\nDescargado para juan camilo sarmiento (z0500754a@saludcastillayleon.es) en Government of Castile and Leon Ministry of Health de ClinicalKey.es por Elsevier en \njunio 02, 2026. Para uso personal exclusivamente. No se permiten otros usos sin autorización. Copyright ©2026. Elsevier Inc. Todos los derechos reservados."
    },
    {
      "pageNumber": 17,
      "text": "1292 SECTION 7 Knee\nfunctional status, magnetic resonance imaging should not be \nroutinely ordered for patients with osteoarthritis of the knee.\nCitation:\nCoventry M. Osteotomy of the upper portion of the tibia for \ndegenerative arthritis. J Bone Joint Surg. 1965;47:984–990.\nLevel of Evidence:\nIV\nSummary:\nIn this classic article, Coventry describes his original lateral closing \nwedge high tibial osteotomy technique and his encouraging \nresults in a case series of 32 patients with varus osteoarthritis of \nthe knee.\nCitation:\nDugdale TW, Noyes FR, Styer D. Preoperative planning for high \ntibial osteotomy. The effect of lateral tibiofemoral separation and \ntibiofemoral length. Clin Orthop Relat Res. 1992;274:248–264.\nLevel of Evidence:\nIV\nSummary:\nThis article describes how to preoperatively plan the correction \nrequired during high tibial osteotomy surgery to restore the \nweight-bearing line (center femoral head to center tibiotalar \njoint) to a point 62.5% across the width of the tibial plateau.\nCitation:\nFelson D, Zhang Y, Anthony J, et al. Weight loss reduces the risk for \nsymptomatic knee osteoarthritis in women: the Framingham \nstudy. Ann Intern Med. 1992;116(7):535.\nLevel of Evidence:\nIV\nSummary:\nThis report on a large case series with long-term follow-up shows \nthat weight loss reduces the risk for symptomatic osteoarthritis in \nwomen.\nCitation:\nHernigou P , Medevielle D, Debeyre J, et al. Proximal tibial osteotomy \nfor osteoarthritis with varus deformity. A ten- to thirteen-year \nfollow-up study. J Bone Joint Surg Am. 1987;69A(3):332–354.\nLevel of Evidence:\nIV\nSummary:\nThis article includes the longest published follow-up of patients \nundergoing opening wedge high tibial osteotomy for varus \nosteoarthritis of the knee and shows good success at a mean of 11 \nyears after surgery.\nCitation:\nKirkley A, Birmingham TB, Litchfield RB, et al. A randomized trial \nof arthroscopic surgery for osteoarthritis of the knee. N Engl J \nMed. 2008;359(11):1097–1107.\nLevel of Evidence:\nI\nSummary:\nThis article reports that arthroscopic surgery for osteoarthritis of the \nknee provides no additional benefit to optimized physical and \nmedical therapy.\nCitation:\nMoseley JB, O’Malley K, Petersen NJ, et al. A controlled trial of \narthroscopic surgery for osteoarthritis of the knee. N Engl J Med. \n2002;347(2):81–88.\nLevel of Evidence:\nI\nSummary:\nThis article reports that the outcomes after arthroscopic lavage or \narthroscopic débridement were no better than those after a \nplacebo procedure in patients with knee osteoarthritis.\nCitation:\nRichmond J, Hunter D, Irrgang J, et al. Treatment of osteoarthritis of \nthe knee (nonarthroplasty). J Am Acad Orthop Surg. \n2009;17(9):591–600.\nLevel of Evidence:\nI\nSummary:\nThis article provides American Academy of Orthopaedic Surgeons–\napproved evidence-based clinical practice guidelines for the \nappropriate nonoperative treatment of knee osteoarthritis.\nCitation:\nRosenberg TD, Paulos LE, Parker RD, et al. The forty-five-degree \nposteroanterior flexion weight-bearing radiograph of the knee. J \nBone Joint Surg Am. 1988;70A(10):1479–1483.\nLevel of Evidence:\nIV\nSummary:\nThis article reports that posteroanterior weight-bearing radiographs \nwith the knee at 45 degrees of flexion were more accurate, more \nspecific, and more sensitive than conventional extension \nweight-bearing AP radiographs.\nDescargado para juan camilo sarmiento (z0500754a@saludcastillayleon.es) en Government of Castile and Leon Ministry of Health de ClinicalKey.es por Elsevier en \njunio 02, 2026. Para uso personal exclusivamente. No se permiten otros usos sin autorización. Copyright ©2026. Elsevier Inc. Todos los derechos reservados."
    },
    {
      "pageNumber": 18,
      "text": "1292.e1CHAPTER 104 Knee Arthritis\n19. B oegård T, Jonsson K. Radiography in osteoarthritis of the \nknee. Skeletal Radiol. 1999;28(11):605–615.\n20. Da vies AP , Calder DA, Marshall T, et  al. Plain radiography in \nthe degenerate knee. A case for change. J Bone Joint Surg Br. \n1999;81(4):632–635.\n21. R osenberg TD, Paulos LE, Parker RD, et  al. The forty-five-\ndegree posteroanterior flexion weight-bearing radiograph of \nthe knee. J Bone Joint Surg Am. 1988;70(10):1479–1483.\n22. C ooke TD, Li J, Scudamore RA. Radiographic assessment of \nbony contributions to knee deformity. Orthop Clin North Am. \n1994;25(3):387–393.\n23. C oventry MB. Upper tibial osteotomy for osteoarthritis. J Bone \nJoint Surg Am. 1985;67(7):1136–1140.\n24. J ackson JP , Waugh W, Green JP . High tibial osteotomy for \nosteoarthritis of the knee. J Bone Joint Surg Br. 1969;51(1):  \n88–94.\n25. P aley D, Herzenberg JE, T etsworth K, et  al. Deformity planning \nfor frontal and sagittal plane corrective osteotomies. Orthop \nClin North Am. 1994;25(3):425–465.\n26. Hs u RW, Himeno S, Coventry MB, et  al. Normal axial \nalignment of the lower extremity and load-bearing distribution \nat the knee. Clin Orthop Relat Res. 1990;255:215–227.\n27. Giffin JR,  Vogrin TM, Zantop T, et  al. Effects of increasing \ntibial slope on the biomechanics of the knee. Am J Sports Med. \n2004;32(2):376–382.\n28. B hattacharyya T, Gale D, Dewire P , et  al. The clinical \nimportance of meniscal tears demonstrated by magnetic \nresonance imaging in osteoarthritis of the knee. J Bone Joint \nSurg Am. 2003;85-A(1):4–9.\n29. Zhang W, Moskowitz RW, Nuki G, et  al. OARSI \nrecommendations for the management of hip and knee \nosteoarthritis, part I: critical appraisal of existing treatment \nguidelines and systematic review of current research evidence. \nOsteoarthr Cartil. 2007;15(9):981–1000.\n30. Zhang W, Moskowitz RW, Nuki G, et  al. OARSI \nrecommendations for the management of hip and knee \nosteoarthritis, part II: OARSI evidence-based, expert consensus \nguidelines. Osteoarthr Cartil. 2008;16(2):137–162.\n31. F elson D, Zhang Y, Anthony J, et  al. Weight loss reduces the \nrisk for symptomatic knee osteoarthritis in women: the \nFramingham study. Ann Intern Med. 1992;116(7):535.\n32. M essier SP , Gutekunst DJ, Davis C, et  al. Weight loss reduces \nknee-joint loads in overweight and obese older adults  \nwith knee osteoarthritis. Arthritis Rheum. 2005;52(7):  \n2026–2032.\n33. B ennell KL, Hinman RS. A review of the clinical evidence for \nexercise in osteoarthritis of the hip and knee. J Sci Med Sport. \n2011;14(1):4–9.\n34. FD A drug safety communication: prescription acetaminophen \nproducts to be limited to 325  mg per dosage unit; boxed \nwarning will highlight potential for severe liver failure. US FDA \nWebsite. www.fda.gov/Drugs/DrugSafety/ucm239821.htm. \nAccessed May 25, 2017.\n35. B rown GA. AAOS clinical practice guideline: treatment of \nosteoarthritis of the knee: evidence-based guideline. J Am Acad \nOrthop Surg. 2013;21(9):577–579.\n36. H anypsiak BT, Shaffer BS. Nonoperative treatment of \nunicompartmental arthritis of the knee. Orthop Clin North Am. \n2005;36(4):401–411.\n37. K irkley A, Webster-Bogaert S, Litchfield R, et  al. The effect of \nbracing on varus gonarthrosis. J Bone Joint Surg Am. 1999;  \n81(4):539–548.\nREFERENCES\n1. K irkley A, Birmingham TB, Litchfield RB, et  al. A randomized \ntrial of arthroscopic surgery for osteoarthritis of the knee. N \nEngl J Med. 2008;359(11):1097–1107.\n2. M oskowitz RW. Primary osteoarthritis: epidemiology, clinical \naspects, and general management. Am J Med. 1987;83(5):  \n5–10.\n3. H iguchi H, Kimura M, Shirakura K, et  al. Factors affecting \nlong-term results after arthroscopic partial meniscectomy. Clin \nOrthop Relat Res. 2000;377:161–168.\n4. La wrence JTR, Argawal N, Ganley TJ. Degeneration of the knee \njoint in skeletally immature patients with a diagnosis of an \nanterior cruciate ligament tear: is there harm in delay of \ntreatment? Am J Sports Med. 2011;39(12):2582–2587.\n5. A ggarwal A, Panarella L, Amendola A. Considerations for \nosteotomy in the ACL deficient knee. Sports Med Arthrosc. \n2005;13(2):109.\n6. B onin N, Ait Si Selmi T, Donell ST, et  al. Anterior cruciate \nreconstruction combined with valgus upper tibial osteotomy: \n12 years follow-up. Knee. 2004;11(6):431–437.\n7. Elk ousy HA, Harner CD. Ligament deficiency with mal \nalignment. Sports Med Arthrosc Rev. 2003;11(2):140–148.\n8. Giffin JR,  Shannon FJ. The role of the high tibial osteotomy in \nthe unstable knee. Sports Med Arthrosc. 2007;15(1):23–31.\n9. She lbourne KD, Stube KC. Anterior cruciate ligament (ACL)-\ndeficient knee with degenerative arthrosis: treatment with an \nisolated autogenous patellar tendon ACL reconstruction. Knee \nSurg Sports Traumatol Arthrosc. 1997;5(3):150–156.\n10. A nderson J, Felson D. Factors associated with osteoarthritis of \nthe knee in the first national Health and Nutrition \nExamination Survey (HANES I): evidence for an association \nwith overweight, race, and physical demands of work. Am J \nEpidemiol. 1988;128(1):179.\n11. F elson DT. Clinical practice. Osteoarthritis of the knee. N Engl \nJ Med. 2006;354(8):841–848.\n12. F elson DT, Niu J, McClennan C, et  al. Knee buckling: \nprevalence, risk factors, and associated limitations in function. \nAnn Intern Med. 2007;147(8):534–540.\n13. L ubowitz JH, Bernardini BJ, Reid JB. Current concepts review: \ncomprehensive physical examination for instability of the knee. \nAm J Sports Med. 2008;36(3):577–594.\n14. S olomon DH, Simel DL, Bates DW, et  al. The rational clinical \nexamination. Does this patient have a torn meniscus or \nligament of the knee? Value of the physical examination. JAMA. \n2001;286(13):1610–1620.\n15. C hang A, Hochberg M, Song J, et  al. Frequency of varus and \nvalgus thrust and factors associated with thrust presence in \npersons with or at higher risk for knee osteoarthritis. Arthritis \nRheum. 2010;62(5):1403–1411.\n16. Er cin E, Kaya I, Sungur I, et  al. History, clinical findings, \nmagnetic resonance imaging, and arthroscopic correlation in \nmeniscal lesions. Knee Surg Sports Traumatol Arthrosc. \n2012;20(5):851–856.\n17. P almieri-Smith RM, Kreinbrink J, Ashton-Miller JA, et  al. \nQuadriceps inhibition induced by an experimental knee joint \neffusion affects knee joint mechanics during a single-legged \ndrop landing. Am J Sports Med. 2007;35(8):1269–1275.\n18. S nyder-Mackler L, De Luca PF, Williams PR, et  al. Reflex \ninhibition of the quadriceps femoris muscle after injury or \nreconstruction of the anterior cruciate ligament. J Bone Joint \nSurg Am. 1994;76(4):555–560.\nDescargado para juan camilo sarmiento (z0500754a@saludcastillayleon.es) en Government of Castile and Leon Ministry of Health de ClinicalKey.es por Elsevier en \njunio 02, 2026. Para uso personal exclusivamente. No se permiten otros usos sin autorización. Copyright ©2026. Elsevier Inc. Todos los derechos reservados."
    },
    {
      "pageNumber": 19,
      "text": "1292.e2 SECTION 7 Knee\nfixation and bone healing in high tibial osteotomies. J Bone \nJoint Surg Br. 2008;90(12):1548–1557.\n56. Coventry MB. Osteotomy of the upper portion of the tibia for \ndegenerative arthritis of the knee. a preliminary report. 1965. \nClin Orthop Relat Res. 1989;248:4–8.\n57. Vainionpää S, Läike E, Kirves P , et al. Tibial osteotomy for \nosteoarthritis of the knee. A five to ten-year follow-up study. J \nBone Joint Surg Am. 1981;63(6):938–946.\n58. Virolainen P , Aro HT. High tibial osteotomy for the treatment \nof osteoarthritis of the knee: a review of the literature and a \nmeta-analysis of follow-up studies. Arch Orthop Trauma Surg. \n2004;124(4):258–261.\n59. Bergenudd H, Johnell O, Redlund-Johnell I, et al. The articular \ncartilage after osteotomy for medial gonarthrosis. Biopsies after \n2 years in 19 cases. Acta Orthop Scand. 1992;63(4):413–416.\n60. Kanamiya T, Naito M, Hara M, et al. The influences of \nbiomechanical factors on cartilage regeneration after high tibial \nosteotomy for knees with medial compartment osteoarthritis: \nclinical and arthroscopic observations. YJARS. 2002;18(7): \n725–729.\n61. Koshino T, Wada S, Ara Y, et al. Regeneration of degenerated \narticular cartilage after high tibial valgus osteotomy for medial \ncompartmental osteoarthritis of the knee. Knee. 2003;10(3): \n229–236.\n62. Odenbring S, Tjörnstrand B, Egund N, et al. Function after \ntibial osteotomy for medial gonarthrosis below aged 50 years. \nActa Orthop Scand. 1989;60(5):527–531.\n63. Brinkman J-M, Luites JWH, Wymenga AB, et al. Early full \nweight bearing is safe in open-wedge high tibial osteotomy. \nActa Orthop. 2010;81(2):193–198.\n64. Takeuchi R, Ishikawa H, Aratake M, et al. Medial opening \nwedge high tibial osteotomy with early full weight bearing. \nArthroscopy. 2009;25(1):46–53.\n65. El-Assal MA, Khalifa YE, Abdel-Hamid MM, et al. Opening-\nwedge high tibial osteotomy without bone graft. Knee Surg \nSports Traumatol Arthrosc. 2010;18(7):961–966.\n66. Brosset T, Pasquier G, Migaud H, et al. Opening wedge high \ntibial osteotomy performed without filling the defect but with \nlocking plate fixation (T omoFix) and early weight-bearing: \nprospective evaluation of bone union, precision and \nmaintenance of correction in 51 cases. Orthop Traumatol Surg \nRes. 2011;97(7):705–711.\n67. Coventry M. Osteotomy of the upper portion of the tibia for \ndegenerative arthritis. J Bone Joint Surg. 1965;47:984–990.\n68. Coogan PG, Fox JA, Fitch RD. Treatment of adolescent Blount \ndisease with the circular external fixation device and \ndistraction osteogenesis. J Pediatr Orthop. 1996;16(4):450–454.\n69. de Pablos J, Alfaro J, Barrios C. Treatment of adolescent Blount \ndisease by asymmetric physeal distraction. J Pediatr Orthop. \n1997;17(1):54–58.\n70. Kamegaya M, Shinohara Y, Shinada Y. Limb lengthening and \ncorrection of angulation deformity: immediate correction by \nusing a unilateral fixator. J Pediatr Orthop. 1996;16(4):477–479.\n71. Rossi R, Bonasia DE, Amendola A. The role of high tibial \nosteotomy in the varus knee. J Am Acad Orthop Surg. \n2011;19(10):590–599.\n72. Phillips M, Krackow K. Distal femoral varus osteotomy: \nindications and surgical technique. Instr Course Lect. \n1999;48:125.\n73. Phillips MJ, Krackow KA. High tibial osteotomy and distal \nfemoral osteotomy for valgus or varus deformity around the \nknee. Instr Course Lect. 1998;47:429–436.\n38. Baker KR, Nelson ME, Felson DT, et al. The efficacy of home \nbased progressive strength training in older adults with knee \nosteoarthritis: a randomized controlled trial. J Rheumatol. \n2001;28(7):1655–1665.\n39. Ettinger WH, Burns R, Messier SP , et al. A randomized trial \ncomparing aerobic exercise and resistance exercise with a \nhealth education program in older adults with knee \nosteoarthritis: the Fitness Arthritis and Seniors Trial (FAST). \nJAMA. 1997;277(1):25–31.\n40. Fransen M, Crosbie J, Edmonds J. Physical therapy is effective \nfor patients with osteoarthritis of the knee: a randomized \ncontrolled clinical trial. J Rheumatol. 2001;28(1): \n156–164.\n41. Arroll B, Goodyear-Smith F. Corticosteroid injections for \nosteoarthritis of the knee: meta-analysis. BMJ. 2004; \n328(7444):869.\n42. Bellamy N, Campbell J, Robinson V , et al. Intraarticular \ncorticosteroid for treatment of osteoarthritis of the knee. \nCochrane Database Syst Rev . 2006;(2):CD005328.\n43. Bjordal JM, Klovning A, Ljunggren AE, et al. Short-term \nefficacy of pharmacotherapeutic interventions in osteoarthritic \nknee pain: a meta-analysis of randomised placebo-controlled \ntrials. Eur J Pain. 2012;11(2):125–138.\n44. Zhu Y, Yuan M, Meng HY, et al. Basic science and clinical \napplication of platelet-rich plasma for cartilage defects and \nosteoarthritis: a review. Osteoarthritis Cartilage. 2013;21(11): \n1627–1637.\n45. Burke J, Hunter M, Kolhe R, et al. Therapeutic potential of \nmesenchymal stem cell based therapy for osteoarthritis. Clin \nTransl Med. 2016;5:27. doi:10.1186/s40169-016-0112-7.\n46. Samson DJ, Grant MD, Ratko TA, et al. Treatment of primary \nand secondary osteoarthritis of the knee. Evid Rep Technol \nAssess (Full Rep). 2007;Sep(157):1–157.\n47. Brouwer RW, Jakma TSC, V erhagen AP , et al. Braces and \northoses for treating osteoarthritis of the knee. Cochrane \nDatabase Syst Rev. 2005;(1):CD004020.\n48. Bradley JD, Heilman DK, Katz BP , et al. Tidal irrigation as \ntreatment for knee osteoarthritis: a sham-controlled, \nrandomized, double-blinded evaluation. Arthritis Rheum. \n2002;46(1):100–108.\n49. Chang RW, Falconer J, Stulberg SD, et al. A randomized, \ncontrolled trial of arthroscopic surgery versus closed-needle \njoint lavage for patients with osteoarthritis of the knee. \nArthritis Rheum. 1993;36(3):289–296.\n50. Moseley JB, O’Malley K, Petersen NJ, et al. A controlled trial of \narthroscopic surgery for osteoarthritis of the knee. N Engl J \nMed. 2002;347(2):81–88.\n51. Dervin GF, Stiell IG, Rody K, et al. Effect of arthroscopic \ndebridement for osteoarthritis of the knee on health-related \nquality of life. J Bone Joint Surg Am. 2003;85A(1):10–19.\n52. Richmond J, Hunter D, Irrgang J, et al. Treatment of \nosteoarthritis of the knee (nonarthroplasty). J Am Acad Orthop \nSurg. 2009;17(9):591–600.\n53. Amendola A, Panarella L. High tibial osteotomy for the \ntreatment of unicompartmental arthritis of the knee. Orthop \nClin North Am. 2005;36(4):497–504.\n54. Bae DK, Song SJ, Y oon KH. Closed-wedge high tibial \nosteotomy using computer-assisted surgery compared to the \nconventional technique. J Bone Joint Surg Br . 2009;91(9): \n1164–1171.\n55. Brinkman J-M, Lobenhoffer P , Agneskirchner JD, et al. \nOsteotomies around the knee: patient selection, stability of \nDescargado para juan camilo sarmiento (z0500754a@saludcastillayleon.es) en Government of Castile and Leon Ministry of Health de ClinicalKey.es por Elsevier en \njunio 02, 2026. Para uso personal exclusivamente. No se permiten otros usos sin autorización. Copyright ©2026. Elsevier Inc. Todos los derechos reservados."
    },
    {
      "pageNumber": 20,
      "text": "1292.e3CHAPTER 104 Knee Arthritis\n93. Parratte S, Argenson J-NA, Pearce O, et al. Medial \nunicompartmental knee replacement in the under-50s. J Bone \nJoint Surg Br. 2009;91(3):351–356.\n94. Lonner JH. A 57-year-old man with osteoarthritis of the knee. \nJAMA. 2003;289:1016–1025.\n95. Pandit H, Beard DJ, Jenkins C, et al. Combined anterior \ncruciate reconstruction and Oxford unicompartmental knee \narthroplasty. J Bone Joint Surg Br . 2006;88(7):887–892.\n96. Pandit H, Van Duren BH, Gallagher JA, et al. Combined \nanterior cruciate reconstruction and Oxford unicompartmental \nknee arthroplasty: in vivo kinematics. Knee. 2008;15(2): \n101–106.\n97. Borus T, Thornhill T. Unicompartmental knee arthroplasty. J \nAm Acad Orthop Surg. 2008;16(1):9–18.\n98. Kuster MS. Exercise recommendations after total joint \nreplacement: a review of the current literature and proposal of \nscientifically based guidelines. Sports Med. 2002;32(7):433–445.\n99. Healy WL, Sharma S, Schwartz B, et al. Athletic activity after \ntotal joint arthroplasty. J Bone Joint Surg Am. 2008;90(10): \n2245–2252.\n100. Puddu G, Franco V . Femoral antivalgus opening wedge \nosteotomy. YOTSM. 2000;8(1):56–60.\n101. Dugdale TW, Noyes FR, Styer D. Preoperative planning for \nhigh tibial osteotomy. The effect of lateral tibiofemoral \nseparation and tibiofemoral length. Clin Orthop Relat Res. \n1992;274:248–264.\n102. French S, Giffin JR, Fowler PJ. High tibial osteotomy. In: \nElAttrache NS, Harner CD, Mirzayan R, et al, eds. Surgical \nTechniques in Sports Medicine. 1st ed. Philadelphia: Lippincott: \nWilliams & Wilkins; 2007:483–498.\n103. Saragaglia D, Blaysat M, Inman D, et al. Outcome of opening \nwedge high tibial osteotomy augmented with a Biosorb wedge \nand fixed with a plate and screws in 124 patients with a mean \nof ten years follow-up. Int Orthop. 2011;35(8):1151–1156.\n104. DeMeo PJ, Johnson EM, Chiang PP , et al. Midterm follow-up \nof opening-wedge high tibial osteotomy. Am J Sports Med. \n2010;38(10):2077–2084.\n105. Akizuki S, Shibakawa A, Takizawa T, et al. The long-term \noutcome of high tibial osteotomy: a ten- to 20-year follow-up. \nJ Bone Joint Surg Br . 2008;90(5):592–596.\n106. Gstöttner M, Michaela G, Pedross F, et al. Long-term outcome \nafter high tibial osteotomy. Arch Orthop Trauma Surg. \n2008;128(1):111–115.\n107. Naudie DDR, Amendola A, Fowler PJ. Opening wedge high \ntibial osteotomy for symptomatic hyperextension-varus thrust. \nAm J Sports Med. 2004;32(1):60–70.\n108. Hernigou P , Medevielle D, Debeyre J, et al. Proximal tibial \nosteotomy for osteoarthritis with varus deformity. A ten to \nthirteen-year follow-up study. J Bone Joint Surg Am. \n1987;69(3):332–354.\n109. Sternheim A, Garbedian S, Backstein D. Distal femoral varus \nosteotomy: unloading the lateral compartment: long-term \nfollow-up of 45 medial closing wedge osteotomies. Orthopedics. \n2011;34(9):e488–e490.\n110. Puddu G, Franco V , Cerullo G, et al. Distal femoral osteotomy \nfor genu valgus correction. Tech Knee Surg. 2009;8(4):257.\n111. Das DHPW, Sijbesma T, Hoekstra HJ, et al. Distal femoral \nopening-wedge osteotomy for lateral compartment \nosteoarthritis of the knee. Open Access Surg. 2008;1:25–29.\n112. Backstein D, Morag G, Hanna S, et al. Long-term follow-up of \ndistal femoral varus osteotomy of the knee. J Arthroplasty. \n2007;22(4 suppl 1):2–6.\n74. Noyes FR, Barber-Westin SD, Hewett TE. High tibial osteotomy \nand ligament reconstruction for varus angulated anterior \ncruciate ligament-deficient knees. Am J Sports Med. 2000;28(3): \n282–296.\n75. Dejour D, Bonin N, Locatelli E. Tibial antirecurvatum \nosteotomies. YOTSM. 2000;8(1):67–70.\n76. Moroni A, Pezzuto V , Pompili M, et al. Proximal osteotomy of \nthe tibia for the treatment of genu recurvatum in adults. J Bone \nJoint Surg Am. 1992;74(4):577–586.\n77. Kim S-J, Park K-H, Kim S-H, et al. Anterior cruciate ligament \nreconstruction improves activity-induced pain in comparison \nwith pain at rest in middle-aged patients with significant \ncartilage degeneration. Am J Sports Med. 2010;38(7):1343–1348.\n78. Shelbourne KD, Wilckens JH. Intraarticular anterior cruciate \nligament reconstruction in the symptomatic arthritic knee. Am \nJ Sports Med. 1993;21(5):685–688, discussion 688–689.\n79. El-Azab H, Halawa A, Anetzberger H, et al. The effect of \nclosed- and open-wedge high tibial osteotomy on tibial slope: a \nretrospective radiological review of 120 cases. J Bone Joint Surg \nBr. 2008;90(9):1193–1197.\n80. Lattermann C, Jakob RP . High tibial osteotomy alone or \ncombined with ligament reconstruction in anterior cruciate \nligament-deficient knees. Knee Surg Sports Traumatol Arthrosc. \n1996;4(1):32–38.\n81. Dejour H, Neyret P , Boileau P , et al. Anterior cruciate \nreconstruction combined with valgus tibial osteotomy. Clin \nOrthop Relat Res. 1994;299:220–228.\n82. Neuschwander DC, Drez D, Paine RM. Simultaneous high \ntibial osteotomy and ACL reconstruction for combined genu \nvarum and symptomatic ACL tear. Orthopedics. 1993;16(6): \n679–684.\n83. Williams RJ, Kelly BT, Wickiewicz TL, et al. The short-term \noutcome of surgical treatment for painful varus arthritis in \nassociation with chronic ACL deficiency. J Knee Surg. \n2003;16(1):9–16.\n84. Bonnin MP , Laurent J-R, Zadegan F, et al. Can patients really \nparticipate in sport after high tibial osteotomy? Knee Surg \nSports Traumatol Arthrosc. 2011;21(1):64–73.\n85. Salzmann GM, Ahrens P , Naal FD, et al. Sporting activity after \nhigh tibial osteotomy for the treatment of medial compartment \nknee osteoarthritis. Am J Sports Med. 2009;37(2):312–318.\n86. van Raaij TM, Bakker W, Reijman M, et al. The effect of high \ntibial osteotomy on the results of total knee arthroplasty: a \nmatched case control study. BMC Musculoskelet Disord. \n2007;8:74.\n87. Hui C, Salmon LJ, Kok A, et al. Long-term survival of high \ntibial osteotomy for medial compartment osteoarthritis of the \nknee. Am J Sports Med. 2011;39(1):64–70.\n88. Tang WC, Henderson IJP . High tibial osteotomy: long term \nsurvival analysis and patients’ perspective. Knee. 2005;12(6): \n410–413.\n89. Laurencin CT, Zelicof SB, Scott RD, et al. Unicompartmental \nversus total knee arthroplasty in the same patient. A \ncomparative study. Clin Orthop Relat Res. 1991;273:151–156.\n90. Bonutti PM, Dethmers DA. Contemporary unicompartmental \nknee arthroplasty: fixed vs mobile bearing. J Arthroplasty. \n2008;23(7 suppl):24–27.\n91. Li MG, Y ao F, Joss B, et al. Mobile vs. fixed bearing unicondylar \nknee arthroplasty: a randomized study on short term clinical \noutcomes and knee kinematics. Knee. 2006;13(5):365–370.\n92. Scott RD. Mobile- versus fixed-bearing unicompartmental knee \narthroplasty. Instr Course Lect. 2010;59:57–60.\nDescargado para juan camilo sarmiento (z0500754a@saludcastillayleon.es) en Government of Castile and Leon Ministry of Health de ClinicalKey.es por Elsevier en \njunio 02, 2026. Para uso personal exclusivamente. No se permiten otros usos sin autorización. Copyright ©2026. Elsevier Inc. Todos los derechos reservados."
    },
    {
      "pageNumber": 21,
      "text": "1292.e4 SECTION 7 Knee\n113. Wang J-W, Hsu C-C. Distal femoral varus osteotomy for \nosteoarthritis of the knee. Surgical technique. J Bone Joint Surg \nAm. 2006;88(suppl 1 Pt 1):100–108.\n114. Gross AE, Hutchison CR. Realignment osteotomy of the \nknee—part 1: distal femoral varus osteotomy for osteoarthritis \nof the valgus knee. YOTSM. 2000;8(2):122–126.\n115. Marti RK, Schroder J, Witteveen A. The closed wedge varus \nsupracondylar osteotomy. YOTSM. 2000;8(1):48–55.\n116. Finkelstein JA, Gross AE, Davis A. Varus osteotomy of the distal \npart of the femur. A survivorship analysis. J Bone Joint Surg \nAm. 1996;78(9):1348–1352.\n117. Healy WL, Anglen JO, Wasilewski SA, et al. Distal femoral \nvarus osteotomy. J Bone Joint Surg Am. 1988;70(1):102–109.\n118. McDermott AG, Finklestein JA, Farine I, et al. Distal femoral \nvarus osteotomy for valgus deformity of the knee. J Bone Joint \nSurg Am. 1988;70(1):110–116.\n119. Miller BS, Downie B, McDonough EB, et al. Complications \nafter medial opening wedge high tibial osteotomy. Arthroscopy. \n2009;25(6):639–646.\n120. Song EK, Seon JK, Park SJ, et al. The complications of high \ntibial osteotomy: closing- versus opening-wedge methods. J \nBone Joint Surg Br. 2010;92(9):1245–1252.\n121. Spahn G. Complications in high tibial (medial opening wedge) \nosteotomy. Arch Orthop Trauma Surg. 2004;124(10):649–653.\nDescargado para juan camilo sarmiento (z0500754a@saludcastillayleon.es) en Government of Castile and Leon Ministry of Health de ClinicalKey.es por Elsevier en \njunio 02, 2026. Para uso personal exclusivamente. No se permiten otros usos sin autorización. Copyright ©2026. Elsevier Inc. Todos los derechos reservados."
    }
  ],
  "keywords": [
    "adolescent",
    "aerobic",
    "bone",
    "cardio",
    "cardiovascular",
    "cycling",
    "fiber",
    "fluid",
    "gastrointestinal",
    "geriatrics",
    "glucose",
    "immature",
    "injury",
    "knee",
    "muscle",
    "nutrition",
    "pain",
    "patella",
    "patellofemoral",
    "protein",
    "recovery",
    "rehabilitation",
    "running",
    "spine",
    "sports medicine",
    "strength",
    "supplement",
    "weight loss"
  ]
}